sonnetsuiteshelper/__init__.py
sonnetsuiteshelper/__main__.py
sonnetsuiteshelper/analysis_tools.py
sonnetsuiteshelper/cli.py
sonnetsuiteshelper/file_generation.py
sonnetsuiteshelper/itteration_tools.py
sonnetsuiteshelper/run_analysis.py
sonnetsuiteshelper-0.4.6.dist-info/AUTHORS.rst
sonnetsuiteshelper-0.4.6.dist-info/LICENSE
sonnetsuiteshelper-0.4.6.dist-info/METADATA
sonnetsuiteshelper-0.4.6.dist-info/WHEEL
sonnetsuiteshelper-0.4.6.dist-info/entry_points.txt
sonnetsuiteshelper-0.4.6.dist-info/top_level.txt
sonnetsuiteshelper-0.4.6.dist-info/RECORD
